CHANGELOG.md
LICENSE
titofisto/__init__.py
titofisto/settings.py
titofisto/storage.py
titofisto/test_settings.py
titofisto/test_urls.py
titofisto/tests.py
titofisto/urls.py
titofisto/views.py
django_titofisto-1.1.0.dist-info/LICENSE
django_titofisto-1.1.0.dist-info/METADATA
django_titofisto-1.1.0.dist-info/WHEEL
django_titofisto-1.1.0.dist-info/RECORD
