Metadata-Version: 2.1
Name: django-titofisto
Version: 1.1.0
Summary: Django Time-Token File Storage
Home-page: https://edugit.org/AlekSIS/libs/django-titofisto
License: Apache-2.0
Keywords: django,storage,media,secure
Author: Dominik George
Author-email: dominik.george@teckids.org
Requires-Python: >=3.9,<4.0
Classifier: Development Status :: 4 - Beta
Classifier: Environment :: Web Environment
Classifier: Framework :: Django
Classifier: Intended Audience :: Developers
Classifier: License :: OSI Approved :: Apache Software License
Classifier: Programming Language :: Python :: 3
Classifier: Programming Language :: Python :: 3.9
Classifier: Programming Language :: Python :: 3.10
Classifier: Programming Language :: Python :: 3.11
Requires-Dist: Django (>4.2,<6.0)
Requires-Dist: shortuuid (>=1.0.11,<2.0.0)
Project-URL: Repository, https://edugit.org/AlekSIS/libs/django-titofisto
